pyqt_feedback_flow/__init__.py
pyqt_feedback_flow/feedback.py
pyqt_feedback_flow-0.3.5.dist-info/LICENSE
pyqt_feedback_flow-0.3.5.dist-info/METADATA
pyqt_feedback_flow-0.3.5.dist-info/WHEEL
pyqt_feedback_flow-0.3.5.dist-info/RECORD
