Metadata-Version: 2.1
Name: pyqt-feedback-flow
Version: 0.3.5
Summary: Show feedback in toast-like notifications
Home-page: https://github.com/firefly-cpp/pyqt-feedback-flow
Keywords: feedback,notifications,toast,pyqt6
Author: Iztok Fister Jr.
Author-email: iztok@iztok-jr-fister.eu
Requires-Python: >=3.10,<4.0
Classifier: Programming Language :: Python :: 3
Classifier: Programming Language :: Python :: 3.10
Classifier: Programming Language :: Python :: 3.11
Classifier: Programming Language :: Python :: 3.12
Provides-Extra: docs
Requires-Dist: PyQt6 (>=6.4.2,<7.0.0)
Requires-Dist: Sphinx (>=5.0,<6.0) ; extra == "docs"
Requires-Dist: emoji (>=2.6.0,<3.0.0)
Requires-Dist: sphinx-rtd-theme (>=1.0.0,<2.0.0) ; extra == "docs"
Project-URL: Repository, https://github.com/firefly-cpp/pyqt-feedback-flow
